{
  "1": "A picture you drew as a child of your imaginary friend",
  "2": "Pallid leather gloves crafted with ivory fingernails",
  "3": "A lock that opens when blood is dripped in its keyhole",
  "4": "Dice made from the knuckles of a notorious charlatan",
  "5": "Clothes stolen from a scarecrow",
  "6": "A ring of keys for forgotten locks",
  "7": "A spinning top carved with four faces: happy, sad, wrathful, and dead",
  "8": "Nails from the coffin of a murderer",
  "9": "The necklace of a sibling who died on the day you were born",
  "10": "A key to the family crypt",
  "11": "A wig from someone executed by beheading",
  "12": "An bouquet of funerary flowers that always looks and smells fresh",
  "13": "An unopened letter to you from your dying father",
  "14": "A switch used to discipline you as a child",
  "15": "A pocket watch that runs backward for an hour every midnight",
  "16": "A music box that plays by itself whenever someone holding it dances",
  "17": "A winter coat stolen from a dying soldier",
  "18": "A walking cane with an iron ferrule that strikes sparks on stone",
  "19": "A bottle of invisible ink that can only be read at sunset",
  "20": "A flag from a ship lost at sea",
  "21": "A wineskin that refills when interred with a dead person for a night",
  "22": "Porcelain doll’s head that always seems to be looking at you",
  "23": "A set of silverware used by a king for his last meal",
  "24": "A wolf’s head wrought in silver that is also a whistle",
  "25": "A spyglass that always shows the world suffering a terrible storm",
  "26": "A small mirror that shows a much older version of the viewer",
  "27": "A cameo with the profile’s face scratched away",
  "28": "A small, worn book of children’s nursery rhymes",
  "29": "If you have any ideas for commands, message Conman#9276 with them",
  "30": "A mummified raven claw",
  "31": "A teacup from a child’s tea set, stained with blood",
  "32": "A broken pendent of a silver dragon that’s always cold to the touch",
  "33": "A little black book that records your dreams, and yours alone, when you sleep",
  "34": "A small locked box that quietly hums a lovely melody at night but you always forget it in the morning",
  "35": "A necklace formed of the interlinked holy symbols of a dozen deities",
  "36": "An inkwell that makes one a little nauseous when staring at it",
  "37": "A hangman’s noose that feels heavier than it should",
  "38": "An old little doll made from a dark, dense wood and missing a hand and a foot",
  "39": "A birdcage into which small birds fly but once inside never eat or leave",
  "40": "A black executioner’s hood",
  "41": "A lepidopterist’s box filled dead moths with skull-like patterns on their wings",
  "42": "A pouch made of flesh, with a sinew drawstring",
  "43": "A jar of pickled ghouls’ tongue",
  "44": "A tiny spool of black thread that never runs out",
  "45": "The wooden hand of a notorious pirate",
  "46": "A tiny clockwork figurine of a dancer that’s missing a gear and doesn’t work",
  "47": "A urn with the ashes of a dead relative",
  "48": "A black wooden pipe that creates puffs of smoke that look like skulls",
  "49": "A hand mirror backed with a bronze depiction of a medusa",
  "50": "A vial of perfume, the scent of which only certain creatures can detect",
  "51": "A bag containing forty-seven humanoid teeth, one of which is rotten",
  "52": "A four-leaf clover pressed inside a book discussing manners and etiquette",
  "53": "A shard of obsidian that always feels warm to the touch",
  "54": "A sheet of parchment upon which is drawn a complex mechanical contraption",
  "55": "A dragon's bony talon hanging from a plain leather necklace",
  "56": "An ornate scabbard that fits no blade you have found so far",
  "57": "An invitation to a party where a murder happened",
  "58": "A blank book whose pages refuse to hold ink, chalk, graphite, or any other substance for marking",
  "59": "A bronze pentacle with an etching of a rat's head in its center",
  "60": "A silver badge in the shape of a five-pointed star",
  "61": "A purple handkerchief embroidered with the name of a powerful archmage",
  "62": "A knife that belonged to a relative",
  "63": "Half of a floorplan for a temple, castle, or some other structure",
  "64": "A glass vial filled with nail clippings",
  "65": "A bit of folded cloth that, when unfolded, turns into a stylish cap",
  "66": "A rectangular metal device with two tiny metal cups on one end that throws sparks when wet",
  "67": "A receipt of deposit at a bank in a far-flung city",
  "68": "A white, sequined glove sized for a human",
  "69": "A diary with seven missing pages",
  "70": "A vest with one hundred tiny pockets",
  "71": "An empty silver snuff box bearing an inscription on the surface that says \"dreams\"",
  "72": "A small, weightless stone block",
  "73": "An iron holy symbol devoted to an unknown god",
  "74": "A tiny sketch portrait of a goblin",
  "75": "A book that tells the story of a legendary hero's rise and fall, with the last chapter missing",
  "76": "An empty glass vial that smells of perfume when opened",
  "77": "A gemstone that looks like a lump of coal when examined by anyone but you",
  "78": "An ancient arrow of elven design",
  "79": "A scrap of cloth from an old banner",
  "80": "A needle that never bends",
  "81": "A rank insignia from a lost legionnaire",
  "82": "An ornate brooch of dwarven design",
  "83": "A tiny silver bell without a clapper",
  "84": "An empty wine bottle bearing a pretty label that says, \"The Wizard of Wines Winery, Red Dragon Crush, 331422-W\"",
  "85": "A mechanical canary inside a gnomish lamp",
  "86": "A mosaic tile with a multicolored, glazed surface",
  "87": "A tiny chest carved to look like it has numerous feet on the bottom",
  "88": "A petrified mouse",
  "89": "A dead sprite inside a clear glass bottle",
  "90": "A black pirate flag adorned with a dragon's skull and crossbones",
  "91": "A metal can that has no opening but sounds as if it is filled with liquid, sand, spiders, or broken glass (your choice)",
  "92": "A tiny mechanical crab or spider that moves about when it’s not being observed",
  "93": "A glass orb filled with water, in which swims a clockwork goldfish",
  "94": "A glass jar containing lard with a label that reads, “Griffon Grease”",
  "95": "A silver spoon with an M engraved on the handle",
  "96": "A wooden box with a ceramic bottom that holds a living worm with a head on each end of its body",
  "97": "A whistle made from gold-colored wood",
  "98": "A metal urn containing the ashes of a hero",
  "99": "A crystal knob from a door",
  "100": "A piece of paper with an undistinguishable face on it"
}
